scrapy_vectors/__init__.py
scrapy_vectors/embeddings.py
scrapy_vectors/feedexport.py
scrapy_vectors-0.2.2.dist-info/licenses/LICENSE
scrapy_vectors-0.2.2.dist-info/METADATA
scrapy_vectors-0.2.2.dist-info/WHEEL
scrapy_vectors-0.2.2.dist-info/top_level.txt
scrapy_vectors-0.2.2.dist-info/RECORD
