Metadata-Version: 2.4
Name: scrapy-vectors
Version: 0.2.2
Summary: Vector embeddings generation and storage for Scrapy
Author: Kyle Kai Hang Tan
License-Expression: ISC
Project-URL: Homepage, https://github.com/kyleissuper/scrapy-vectors
Project-URL: Repository, https://github.com/kyleissuper/scrapy-vectors
Project-URL: Issues, https://github.com/kyleissuper/scrapy-vectors/issues
Keywords: scrapy,vectors,embeddings,s3,llm
Classifier: Development Status :: 4 - Beta
Classifier: Intended Audience :: Developers
Classifier: Operating System :: POSIX :: Linux
Classifier: Operating System :: MacOS
Classifier: Programming Language :: Python :: 3
Classifier: Programming Language :: Python :: 3.9
Classifier: Programming Language :: Python :: 3.10
Classifier: Programming Language :: Python :: 3.11
Classifier: Programming Language :: Python :: 3.12
Classifier: Programming Language :: Python :: 3.13
Classifier: Framework :: Scrapy
Classifier: Topic :: Internet :: WWW/HTTP
Classifier: Topic :: Software Development :: Libraries :: Python Modules
Requires-Python: >=3.9
License-File: LICENSE
Requires-Dist: scrapy>=2.0
Requires-Dist: litellm[proxy]>=1.0.0
Requires-Dist: boto3>=1.40.23
Requires-Dist: botocore>=1.40.23
Dynamic: license-file
